botpilot/__init__.py
botpilot/main.py
botpilot/commands/__init__.py
botpilot/commands/init.py
botpilot/templates/shared/app.ini.j2
botpilot/templates/shared/db_connection.py.j2
botpilot/templates/shared/emailer.py.j2
botpilot/templates/shared/logger.py.j2
botpilot/templates/web_bot/web_bot.py.j2
botpilot-0.1.4.dist-info/licenses/LICENSE
botpilot-0.1.4.dist-info/METADATA
botpilot-0.1.4.dist-info/WHEEL
botpilot-0.1.4.dist-info/entry_points.txt
botpilot-0.1.4.dist-info/top_level.txt
botpilot-0.1.4.dist-info/RECORD
