Metadata-Version: 2.4
Name: botpilot
Version: 0.1.4
Summary: A CLI toolkit for automating web bots and reconciliation bots.
Author-email: Patrick Adu-Amankwah <adu-amankwahp@stanbic.com.gh>
License: MIT
Requires-Python: >=3.7
License-File: LICENSE
Requires-Dist: typer[all]
Requires-Dist: jinja2
Requires-Dist: python-decouple
Requires-Dist: pandas
Requires-Dist: oracledb
Requires-Dist: requests
Dynamic: license-file
